romanisim/catalog.py
romanisim/l3.py
romanisim/ramp.py
romanisim/persistence.py
romanisim/ris_make_utils.py
romanisim/util.py
romanisim/ramp_fit_casertano.pyx
romanisim/velocity_aberration.py
romanisim/__init__.py
romanisim/gaia.py
romanisim/psf.py
romanisim/ramp_fit_casertano.cpython-312-darwin.so
romanisim/wcs.py
romanisim/ramp_fit_casertano.c
romanisim/cr.py
romanisim/nonlinearity.py
romanisim/parameters.py
romanisim/l1.py
romanisim/image.py
romanisim/bandpass.py
romanisim/tests/test_catalog.py
romanisim/tests/test_psf.py
romanisim/tests/test_ramp.py
romanisim/tests/test_l3.py
romanisim/tests/dms_requirement_tests.json
romanisim/tests/test_dms_requirements.py
romanisim/tests/test_gaia.py
romanisim/tests/test_image.py
romanisim/tests/test_persistence.py
romanisim/tests/__init__.py
romanisim/tests/test_util.py
romanisim/tests/test_cr.py
romanisim/tests/test_bandpass.py
romanisim/tests/test_linear.py
romanisim/tests/test_wcs.py
romanisim/tests/test_l1.py
romanisim/tests/test_ris_make_utils.py
romanisim/regtest/__init__.py
romanisim/regtest/test_l1.py
romanisim/data/COSMOS2020_CLASSIC_R1_v2.2_p3_Streamlined.fits
romanisim/data/Roman_effarea_20201130.csv
romanisim/data/gaia-270-66-2027-06-01.ecsv
romanisim/data/cat-97599.fits
romanisim/data/Roman_effarea_tables_20240327/Roman_effarea_v8_SCA08_20240301.ecsv
romanisim/data/Roman_effarea_tables_20240327/Roman_effarea_v8_SCA18_20240301.ecsv
romanisim/data/Roman_effarea_tables_20240327/Roman_effarea_v8_SCA16_20240301.ecsv
romanisim/data/Roman_effarea_tables_20240327/Roman_effarea_v8_SCA01_20240301.ecsv
romanisim/data/Roman_effarea_tables_20240327/Roman_effarea_v8_SCA05_20240301.ecsv
romanisim/data/Roman_effarea_tables_20240327/Roman_effarea_v8_SCA12_20240301.ecsv
romanisim/data/Roman_effarea_tables_20240327/Roman_effarea_v8_SCA02_20240301.ecsv
romanisim/data/Roman_effarea_tables_20240327/Roman_effarea_v8_SCA15_20240301.ecsv
romanisim-0.12.0.dist-info/RECORD
romanisim-0.12.0.dist-info/WHEEL
romanisim-0.12.0.dist-info/top_level.txt
romanisim-0.12.0.dist-info/METADATA
romanisim-0.12.0.dist-info/licenses/LICENSE
