Metadata-Version: 2.4
Name: romanisim
Version: 0.12.0
Summary: Nancy Grace Roman Space Telescope WFI Simulator
Author: STScI
Project-URL: Tracker, https://github.com/spacetelescope/romanisim/issues
Project-URL: Documentation, https://romanisim.readthedocs.io/en/stable/
Project-URL: Source Code, https://github.com/spacetelescope/romanisim
Classifier: Intended Audience :: Science/Research
Classifier: Topic :: Scientific/Engineering :: Astronomy
Classifier: Operating System :: MacOS :: MacOS X
Classifier: Operating System :: POSIX
Classifier: Programming Language :: Python :: 3
Classifier: Programming Language :: Python :: 3 :: Only
Classifier: Programming Language :: Python :: 3.11
Requires-Python: <3.14,>=3.11
License-File: LICENSE
Requires-Dist: asdf>=4.1.0
Requires-Dist: astropy>=6.0
Requires-Dist: astropy_healpix>=1.1.2
Requires-Dist: astroquery>=0.4.11
Requires-Dist: crds>=13.0.2
Requires-Dist: defusedxml>=0.5.0
Requires-Dist: galsim>=2.5.1
Requires-Dist: roman_datamodels<0.31.0,>=0.29.0
Requires-Dist: gwcs>=0.25.0
Requires-Dist: numpy>1.26
Requires-Dist: photutils>=2.3.0
Provides-Extra: docs
Requires-Dist: sphinx<7; extra == "docs"
Requires-Dist: sphinx-automodapi; extra == "docs"
Requires-Dist: sphinx-rtd-theme; extra == "docs"
Requires-Dist: stsci-rtd-theme; extra == "docs"
Requires-Dist: sphinx-astropy; extra == "docs"
Requires-Dist: sphinx-asdf>=0.1.1; extra == "docs"
Requires-Dist: tomli; python_version < "3.11" and extra == "docs"
Provides-Extra: test
Requires-Dist: ci-watson>=0.3.0; extra == "test"
Requires-Dist: pytest>=9.0; extra == "test"
Requires-Dist: pytest-openfiles>=0.5.0; extra == "test"
Requires-Dist: pytest-doctestplus>=0.10.0; extra == "test"
Requires-Dist: pytest-cov>=2.9.0; extra == "test"
Requires-Dist: stpsf>=2.1.0; extra == "test"
Dynamic: license-file
